jumanji/__init__.py
jumanji/env.py
jumanji/py.typed
jumanji/registration.py
jumanji/specs.py
jumanji/tree_utils.py
jumanji/types.py
jumanji/version.py
jumanji/viewer.py
jumanji/wrappers.py
jumanji/environments/__init__.py
jumanji/environments/commons/__init__.py
jumanji/environments/commons/graph_view_utils.py
jumanji/environments/commons/maze_utils/__init__.py
jumanji/environments/commons/maze_utils/maze_generation.py
jumanji/environments/commons/maze_utils/maze_rendering.py
jumanji/environments/commons/maze_utils/stack.py
jumanji/environments/logic/__init__.py
jumanji/environments/logic/game_2048/__init__.py
jumanji/environments/logic/game_2048/env.py
jumanji/environments/logic/game_2048/types.py
jumanji/environments/logic/game_2048/utils.py
jumanji/environments/logic/game_2048/viewer.py
jumanji/environments/logic/graph_coloring/__init__.py
jumanji/environments/logic/graph_coloring/env.py
jumanji/environments/logic/graph_coloring/generator.py
jumanji/environments/logic/graph_coloring/types.py
jumanji/environments/logic/graph_coloring/viewer.py
jumanji/environments/logic/minesweeper/__init__.py
jumanji/environments/logic/minesweeper/constants.py
jumanji/environments/logic/minesweeper/done.py
jumanji/environments/logic/minesweeper/env.py
jumanji/environments/logic/minesweeper/generator.py
jumanji/environments/logic/minesweeper/reward.py
jumanji/environments/logic/minesweeper/types.py
jumanji/environments/logic/minesweeper/utils.py
jumanji/environments/logic/minesweeper/viewer.py
jumanji/environments/logic/rubiks_cube/__init__.py
jumanji/environments/logic/rubiks_cube/constants.py
jumanji/environments/logic/rubiks_cube/env.py
jumanji/environments/logic/rubiks_cube/generator.py
jumanji/environments/logic/rubiks_cube/reward.py
jumanji/environments/logic/rubiks_cube/types.py
jumanji/environments/logic/rubiks_cube/utils.py
jumanji/environments/logic/rubiks_cube/viewer.py
jumanji/environments/logic/sliding_tile_puzzle/__init__.py
jumanji-1.1.1.dist-info/licenses/LICENSE
jumanji-1.1.1.dist-info/METADATA
jumanji-1.1.1.dist-info/WHEEL
jumanji-1.1.1.dist-info/top_level.txt
jumanji-1.1.1.dist-info/RECORD
