Metadata-Version: 2.4
Name: jumanji
Version: 1.1.1
Summary: A diverse suite of scalable reinforcement learning environments in JAX
Author-email: InstaDeep Ltd <clement.bonnet16@gmail.com>
License:                                  Apache License
Project-URL: Homepage, https://github.com/instadeep/jumanji
Project-URL: Bug Tracker, https://github.com/instadeep/jumanji/issues
Project-URL: Documentation, https://instadeepai.github.io/jumanji
Keywords: reinforcement-learning,python,jax
Classifier: Development Status :: 5 - Production/Stable
Classifier: Environment :: Console
Classifier: Intended Audience :: Science/Research
Classifier: Intended Audience :: Developers
Classifier: Operating System :: OS Independent
Classifier: Programming Language :: Python
Classifier: Programming Language :: Python :: 3.10
Classifier: Programming Language :: Python :: 3.11
Classifier: Programming Language :: Python :: 3.12
Classifier: Topic :: Scientific/Engineering :: Artificial Intelligence
Classifier: Topic :: Software Development :: Libraries :: Python Modules
Classifier: License :: OSI Approved :: Apache Software License
Requires-Python: >=3.10
License-File: LICENSE
Requires-Dist: chex>=0.1.3
Requires-Dist: dm-env>=1.5
Requires-Dist: esquilax>=2.0.0
Requires-Dist: gymnasium>=1.0
Requires-Dist: huggingface-hub
Requires-Dist: jax>=0.2.26
Requires-Dist: matplotlib>=3.8.0
Requires-Dist: numpy>=1.19.5
Requires-Dist: Pillow>=9.0.0
Requires-Dist: typing-extensions>=4.0.0
Provides-Extra: dev
Requires-Dist: coverage; extra == "dev"
Requires-Dist: livereload; extra == "dev"
Requires-Dist: mkdocs==1.6.1; extra == "dev"
Requires-Dist: mkdocs-git-revision-date-plugin==0.3.2; extra == "dev"
Requires-Dist: mkdocs-include-markdown-plugin==7.1.1; extra == "dev"
Requires-Dist: mkdocs-material==9.5.45; extra == "dev"
Requires-Dist: mkdocs-mermaid2-plugin==1.1.0; extra == "dev"
Requires-Dist: mkdocs_autorefs==1.2.0; extra == "dev"
Requires-Dist: mkdocstrings[python]==0.27.0; extra == "dev"
Requires-Dist: mknotebooks==0.8.0; extra == "dev"
Requires-Dist: mypy; extra == "dev"
Requires-Dist: pre-commit; extra == "dev"
Requires-Dist: promise; extra == "dev"
Requires-Dist: pymdown-extensions; extra == "dev"
Requires-Dist: pytest==7.0.1; extra == "dev"
Requires-Dist: pytest-cov; extra == "dev"
Requires-Dist: pytest-mock; extra == "dev"
Requires-Dist: pytest-parallel; extra == "dev"
Requires-Dist: pytest-xdist; extra == "dev"
Requires-Dist: scipy>=1.7.3; extra == "dev"
Requires-Dist: testfixtures; extra == "dev"
Provides-Extra: train
Requires-Dist: distrax>=0.1.5; extra == "train"
Requires-Dist: dm-haiku; extra == "train"
Requires-Dist: hydra-core==1.3; extra == "train"
Requires-Dist: neptune-client==0.16.15; extra == "train"
Requires-Dist: optax>=0.1.4; extra == "train"
Requires-Dist: rlax>=0.1.4; extra == "train"
Requires-Dist: tensorboardX==2.5.1; extra == "train"
Requires-Dist: tqdm>=4.64.1; extra == "train"
Dynamic: license-file
